calc_package_washoliver/__init__.py
calc_package_washoliver-0.1.0.dist-info/licenses/LICENSE
calc_package_washoliver-0.1.0.dist-info/METADATA
calc_package_washoliver-0.1.0.dist-info/WHEEL
calc_package_washoliver-0.1.0.dist-info/top_level.txt
calc_package_washoliver-0.1.0.dist-info/RECORD
