Metadata-Version: 2.4
Name: calc_package_washoliver
Version: 0.1.0
Summary: Pacote de cálculo simples criado para publicação no PyPI.
Author: washoliver
Requires-Python: >=3.7
License-File: LICENSE
Dynamic: author
Dynamic: description
Dynamic: description-content-type
Dynamic: license-file
Dynamic: requires-python
Dynamic: summary
